metachrome/__init__.py
metachrome/batch_processor.py
metachrome/image_processor.py
metachrome/main.py
metachrome/segmentation_postprocessing.py
metachrome-1.0.0.dist-info/licenses/LICENSE
metachrome-1.0.0.dist-info/METADATA
metachrome-1.0.0.dist-info/WHEEL
metachrome-1.0.0.dist-info/entry_points.txt
metachrome-1.0.0.dist-info/top_level.txt
metachrome-1.0.0.dist-info/RECORD
