Metadata-Version: 2.4
Name: metachrome
Version: 1.0.0
Summary: Metaphase Chromosome Analysis with Napari
Home-page: https://github.com/yourusername/metachrome
Author: Md Abdul Kader Sagar
Author-email: Md Abdul Kader Sagar <sagarm2@nih.gov>
Maintainer-email: Md Abdul Kader Sagar <sagarm2@nih.gov>
License: MIT
Project-URL: Homepage, https://github.com/yourusername/metachrome
Project-URL: Repository, https://github.com/yourusername/metachrome
Project-URL: Documentation, https://github.com/yourusername/metachrome#readme
Project-URL: Bug Tracker, https://github.com/yourusername/metachrome/issues
Keywords: chromosome,analysis,napari,bioinformatics,image-processing
Classifier: Development Status :: 4 - Beta
Classifier: Intended Audience :: Science/Research
Classifier: License :: OSI Approved :: MIT License
Classifier: Operating System :: OS Independent
Classifier: Programming Language :: Python :: 3
Classifier: Programming Language :: Python :: 3.8
Classifier: Programming Language :: Python :: 3.9
Classifier: Programming Language :: Python :: 3.10
Classifier: Programming Language :: Python :: 3.11
Classifier: Topic :: Scientific/Engineering :: Bio-Informatics
Classifier: Topic :: Scientific/Engineering :: Image Processing
Requires-Python: >=3.8
License-File: LICENSE
Requires-Dist: napari>=0.4.0
Requires-Dist: numpy>=1.20.0
Requires-Dist: pandas>=1.3.0
Requires-Dist: scikit-image>=0.18.0
Requires-Dist: scipy>=1.7.0
Requires-Dist: matplotlib>=3.3.0
Requires-Dist: magicgui>=0.2.0
Requires-Dist: qtpy>=1.9.0
Requires-Dist: superqt>=0.2.0
Requires-Dist: cellpose>=2.0.0
Requires-Dist: Pillow>=8.0.0
Provides-Extra: dev
Requires-Dist: pytest>=6.0; extra == "dev"
Requires-Dist: pytest-cov>=2.0; extra == "dev"
Requires-Dist: black>=21.0; extra == "dev"
Requires-Dist: flake8>=3.8; extra == "dev"
Dynamic: author
Dynamic: home-page
Dynamic: license-file
Dynamic: requires-python
